<?xml version="1.0" encoding="UTF-8"?>
<persistence version="2.1" xmlns="http://xmlns.jcp.org/xml/ns/persistence" xmlns:xsi="http://www.w3.org/2001/XMLSchema-instance" xsi:schemaLocation="http://xmlns.jcp.org/xml/ns/persistence http://xmlns.jcp.org/xml/ns/persistence/persistence_2_1.xsd">
  <persistence-unit name="PremAanganManagerPU" transaction-type="RESOURCE_LOCAL">
    <provider>org.eclipse.persistence.jpa.PersistenceProvider</provider>
    <class>premaanganmanager.configurable.entity.ApplicationLabels</class>
    <class>premaanganmanager.configurable.entity.StudentFamilyInfo</class>
    <class>premaanganmanager.configurable.entity.Timetable</class>
    <class>premaanganmanager.configurable.entity.ClassStudent</class>
    <class>premaanganmanager.configurable.entity.Religion</class>
    <class>premaanganmanager.configurable.entity.Student</class>
    <class>premaanganmanager.configurable.entity.TimetableClass</class>
    <class>premaanganmanager.configurable.entity.Teacher</class>
    <class>premaanganmanager.configurable.entity.TeacherSubject</class>
    <class>premaanganmanager.configurable.entity.BatchClassCourse</class>
    <class>premaanganmanager.configurable.entity.TeacherFamilyInfo</class>
    <class>premaanganmanager.configurable.entity.Class</class>
    <class>premaanganmanager.configurable.entity.Course</class>
    <class>premaanganmanager.configurable.entity.CourseDuration</class>
    <class>premaanganmanager.configurable.entity.FamilyInfo</class>
    <class>premaanganmanager.configurable.entity.Timebreak</class>
    <class>premaanganmanager.configurable.entity.Subject</class>
    <class>premaanganmanager.configurable.entity.StudentAttendance</class>
    <class>premaanganmanager.configurable.entity.TeacherAttendance</class>
    <class>premaanganmanager.configurable.entity.Batch</class>
    <class>premaanganmanager.configurable.entity.Users</class>
    <properties>
      <property name="javax.persistence.jdbc.url" value="jdbc:sqlite:PremAanganManager.sqlite"/>
      <property name="javax.persistence.jdbc.user" value=""/>
      <property name="javax.persistence.jdbc.driver" value="org.sqlite.JDBC"/>
      <property name="javax.persistence.jdbc.password" value=""/>
    </properties>
  </persistence-unit>
</persistence>
